__init__.py
krasue.py
PyKrasue-0.0.11.dist-info/LICENSE
PyKrasue-0.0.11.dist-info/METADATA
PyKrasue-0.0.11.dist-info/WHEEL
PyKrasue-0.0.11.dist-info/top_level.txt
PyKrasue-0.0.11.dist-info/RECORD
