Metadata-Version: 2.1
Name: PyKrasue
Version: 0.0.11
Summary: A GPU accelerated pygame/arcade alternative
Author-email: Andrew Mengede <amengede27@outlook.com>
Project-URL: Homepage, https://github.com/amengede/pykrasue
Project-URL: Issues, https://github.com/amengede/pykrasue/issues
Classifier: Programming Language :: Python :: 3
Classifier: License :: OSI Approved :: MIT License
Classifier: Operating System :: OS Independent
Requires-Python: >=3.10
License-File: LICENSE
Requires-Dist: glfw
